<?xml version="1.0"?>
<scenes pages="10">
    <scene src='https://avatars.mds.yandex.net/get-zen_doc/1781308/pub_5cc0bd4755489700b33e54ef_5cc0cccc72f48900b3ff69c7/scale_1200'>
        Первая история - "Лица на портретах".
    </scene>

    <scene src='http://img-fotki.yandex.ru/get/5602/iskander777888.1/0_4373c_cdd6c5a8_XL.jpg'>
        Один человек заблудился в лесу.
    </scene>

    <scene src='https://pics.ru/wp-content/uploads/2015/07/hor1.jpg'>
        Он долго блуждал и, в конце концов, в сумерках натолкнулся на хижину.
    </scene>

    <scene src='https://static3.depositphotos.com/1004186/177/i/600/depositphotos_1773123-stock-photo-terrible-room.jpg'>
        Внутри никого не было, и он решил лечь спать.
    </scene>

    <scene src='https://cdn.igromania.ru/mnt/articles/0/6/8/b/c/d/28091/html/img/1f5e5d175422144f.jpg'>
        Но он долго не мог заснуть, потому что на стенах висели портреты каких-то людей, и ему казалось, что они зловеще смотрят на него.
    </scene>

    <scene src='https://proza.ru/pics/2020/10/17/86.jpg'>
        В конце концов он заснул от усталости.
    </scene>

    <scene src='https://static4.depositphotos.com/1006844/283/i/600/depositphotos_2834885-stock-photo-room-after-a-fire.jpg'>
        Утром его разбудил яркий солнечный свет.
    </scene>

    <scene src='http://pm1.narvii.com/7860/971cc5198e2b35eb8db5a77440c6027521f13cecr1-717-501v2_uhq.jpg'>
        На стенах не было никаких картин. Это были окна.
    </scene>
</scenes>